genbu/__init__.py
genbu/cli.py
genbu/combinators.py
genbu/exceptions.py
genbu/infer.py
genbu/infer_params.py
genbu/normalize.py
genbu/params.py
genbu/py.typed
genbu/usage.py
tests/__init__.py
tests/strategies.py
tests/test_cli.py
tests/test_combinators.py
tests/test_genbu.py
tests/test_infer.py
tests/test_infer_params.py
tests/test_params.py
tests/test_usage.py
genbu-0.2.1.dist-info/LICENSE
genbu-0.2.1.dist-info/METADATA
genbu-0.2.1.dist-info/WHEEL
genbu-0.2.1.dist-info/top_level.txt
genbu-0.2.1.dist-info/RECORD
