Metadata-Version: 2.1
Name: genbu
Version: 0.2.1
Summary: Create CLIs using parser combinators and type hints
Home-page: https://github.com/lggruspe/genbu
Author: Levi Gruspe
Author-email: mail.levig@gmail.com
License: UNKNOWN
Platform: UNKNOWN
Classifier: License :: OSI Approved :: MIT License
Classifier: Programming Language :: Python :: 3
Classifier: Programming Language :: Python :: 3.6
Classifier: Programming Language :: Python :: 3.7
Classifier: Programming Language :: Python :: 3.8
Classifier: Programming Language :: Python :: 3.9
Requires-Python: >=3.6
